Metadata-Version: 2.2
Name: certora-cli-alpha-rahav-CERT-9018_solc6.6
Version: 20250525.15.41.682053
Summary: Runner for the Certora Prover
Home-page: https://pypi.org/project/certora-cli-alpha-rahav-CERT-9018_solc6.6
Author: Certora
Author-email: support@certora.com
License: GPL-3.0-only
Project-URL: Documentation, https://docs.certora.com/en/latest/
Project-URL: Source, https://github.com/Certora/CertoraProver
Classifier: Programming Language :: Python :: 3
Classifier: License :: OSI Approved :: GNU General Public License v3 (GPLv3)
Classifier: Operating System :: OS Independent
Requires-Python: >=3.8
License-File: LICENSE
Requires-Dist: click
Requires-Dist: json5
Requires-Dist: pycryptodome
Requires-Dist: requests
Requires-Dist: rich
Requires-Dist: sly
Requires-Dist: tabulate
Requires-Dist: tqdm
Requires-Dist: StrEnum
Requires-Dist: universalmutator
Requires-Dist: jinja2
Dynamic: author
Dynamic: author-email
Dynamic: classifier
Dynamic: description
Dynamic: description-content-type
Dynamic: home-page
Dynamic: license
Dynamic: project-url
Dynamic: requires-dist
Dynamic: requires-python
Dynamic: summary
